libfolder/__init__.py
libfolder/reverse-swapping.py
libfolder/reverse_swapping.py
Reverse_value-0.0.0.1.dist-info/LICENCE
Reverse_value-0.0.0.1.dist-info/METADATA
Reverse_value-0.0.0.1.dist-info/WHEEL
Reverse_value-0.0.0.1.dist-info/top_level.txt
Reverse_value-0.0.0.1.dist-info/RECORD
