Metadata-Version: 2.1
Name: Reverse-value
Version: 0.0.0.1
Summary: A Reverse Swap package
Home-page: UNKNOWN
Author: Harshith Raj
Author-email: <harshith1900@gmail.com>
License: UNKNOWN
Keywords: python
Platform: UNKNOWN
Classifier: License :: OSI Approved :: GNU Lesser General Public License v2 (LGPLv2)
Classifier: Intended Audience :: Developers
Classifier: Programming Language :: Python :: 3
Classifier: Operating System :: Unix
Classifier: Operating System :: MacOS :: MacOS X
Classifier: Operating System :: Microsoft :: Windows
License-File: LICENCE
